aceditor/__init__.py
aceditor/__metadata__/DISCLIAIMER.md
aceditor/__metadata__/LICENSE
aceditor/__metadata__/README.md
aceditor/__metadata__/__init__.py
aceditor/__metadata__/requirements.txt
aceditor/example/client/README.md
aceditor/example/client/index.html
aceditor/example/client/script.js
aceditor/example/client/style.css
aceditor/example/client/src/README.md
aceditor/example/client/src/ace.js
aceditor/example/client/src/ext-modelist.js
aceditor/example/client/src/ext-statusbar.js
aceditor/example/client/src/theme-tomorrow_night_bright.js
aceditor/example/server/README.md
aceditor/example/server/ACE/api.py
aceditor-0.5.0.dist-info/METADATA
aceditor-0.5.0.dist-info/WHEEL
aceditor-0.5.0.dist-info/top_level.txt
aceditor-0.5.0.dist-info/RECORD
